nonebot_plugin_yinyu/__init__.py
nonebot_plugin_yinyu-0.0.6.dist-info/LICENSE
nonebot_plugin_yinyu-0.0.6.dist-info/METADATA
nonebot_plugin_yinyu-0.0.6.dist-info/WHEEL
nonebot_plugin_yinyu-0.0.6.dist-info/RECORD
