Metadata-Version: 2.1
Name: nonebot-plugin-yinyu
Version: 0.0.6
Summary: 一个语句瑟瑟化插件
Home-page: https://github.com/shi-yingyingjiang/nonebot-plugin-yinyu
License: MIT
Author: shiyingyingjiang
Author-email: 2798134864@qq.com
Requires-Python: >=3.8
Classifier: License :: OSI Approved :: MIT License
Classifier: Programming Language :: Python :: 3
Classifier: Programming Language :: Python :: 3.8
Classifier: Programming Language :: Python :: 3.9
Classifier: Programming Language :: Python :: 3.10
Classifier: Programming Language :: Python :: 3.11
Classifier: Programming Language :: Python :: 3.12
Requires-Dist: nonebot2 (>=2.0.0)
Requires-Dist: yinglish (>=1.0.1)
Project-URL: Repository, https://github.com/shi-yingyingjiang/nonebot-plugin-yinyu
